leo_win_os_info_mcp/__init__.py
leo_win_os_info_mcp/main.py
leo_win_os_info_mcp-0.1.2.dist-info/METADATA
leo_win_os_info_mcp-0.1.2.dist-info/WHEEL
leo_win_os_info_mcp-0.1.2.dist-info/entry_points.txt
leo_win_os_info_mcp-0.1.2.dist-info/top_level.txt
leo_win_os_info_mcp-0.1.2.dist-info/RECORD
